{
 "count": 135,
 "episodes": [
  {
   "date": "2014-01-28",
   "title": "140128ノーブレーキのオリジンアワー",
   "page": "https://www.fmnaha.jp/podcast_audio/140128%e3%83%8e%e3%83%bc%e3%83%96%e3%83%ac%e3%83%bc%e3%82%ad%e3%81%ae%e3%82%aa%e3%83%aa%e3%82%b8%e3%83%b3%e3%82%a2%e3%83%af%e3%83%bc"
  },
  {
   "date": "2014-02-04",
   "title": "140204ノーブレーキのオリジンアワー",
   "page": "https://www.fmnaha.jp/podcast_audio/140204%e3%83%8e%e3%83%bc%e3%83%96%e3%83%ac%e3%83%bc%e3%82%ad%e3%81%ae%e3%82%aa%e3%83%aa%e3%82%b8%e3%83%b3%e3%82%a2%e3%83%af%e3%83%bc"
  },
  {
   "date": "2014-02-11",
   "title": "140211ノーブレーキのオリジンアワー",
   "page": "https://www.fmnaha.jp/podcast_audio/140211%e3%83%8e%e3%83%bc%e3%83%96%e3%83%ac%e3%83%bc%e3%82%ad%e3%81%ae%e3%82%aa%e3%83%aa%e3%82%b8%e3%83%b3%e3%82%a2%e3%83%af%e3%83%bc"
  },
  {
   "date": "2014-02-18",
   "title": "140218ノーブレーキのオリジンアワー",
   "page": "https://www.fmnaha.jp/podcast_audio/140218%e3%83%8e%e3%83%bc%e3%83%96%e3%83%ac%e3%83%bc%e3%82%ad%e3%81%ae%e3%82%aa%e3%83%aa%e3%82%b8%e3%83%b3%e3%82%a2%e3%83%af%e3%83%bc"
  },
  {
   "date": "2014-02-25",
   "title": "140225ノーブレーキのオリジンアワー",
   "page": "https://www.fmnaha.jp/podcast_audio/140225%e3%83%8e%e3%83%bc%e3%83%96%e3%83%ac%e3%83%bc%e3%82%ad%e3%81%ae%e3%82%aa%e3%83%aa%e3%82%b8%e3%83%b3%e3%82%a2%e3%83%af%e3%83%bc"
  },
  {
   "date": "2014-03-04",
   "title": "140304ノーブレーキのオリジンアワー",
   "page": "https://www.fmnaha.jp/podcast_audio/140304%e3%83%8e%e3%83%bc%e3%83%96%e3%83%ac%e3%83%bc%e3%82%ad%e3%81%ae%e3%82%aa%e3%83%aa%e3%82%b8%e3%83%b3%e3%82%a2%e3%83%af%e3%83%bc"
  },
  {
   "date": "2014-03-11",
   "title": "140311ノーブレーキのオリジンアワー",
   "page": "https://www.fmnaha.jp/podcast_audio/140311%e3%83%8e%e3%83%bc%e3%83%96%e3%83%ac%e3%83%bc%e3%82%ad%e3%81%ae%e3%82%aa%e3%83%aa%e3%82%b8%e3%83%b3%e3%82%a2%e3%83%af%e3%83%bc"
  },
  {
   "date": "2014-03-18",
   "title": "140318ノーブレーキのオリジンアワー",
   "page": "https://www.fmnaha.jp/podcast_audio/140318%e3%83%8e%e3%83%bc%e3%83%96%e3%83%ac%e3%83%bc%e3%82%ad%e3%81%ae%e3%82%aa%e3%83%aa%e3%82%b8%e3%83%b3%e3%82%a2%e3%83%af%e3%83%bc"
  },
  {
   "date": "2014-03-25",
   "title": "140325ノーブレーキのオリジンアワー",
   "page": "https://www.fmnaha.jp/podcast_audio/140325%e3%83%8e%e3%83%bc%e3%83%96%e3%83%ac%e3%83%bc%e3%82%ad%e3%81%ae%e3%82%aa%e3%83%aa%e3%82%b8%e3%83%b3%e3%82%a2%e3%83%af%e3%83%bc"
  },
  {
   "date": "2014-04-01",
   "title": "140401ノーブレーキのオリジンアワー",
   "page": "https://www.fmnaha.jp/podcast_audio/140401%e3%83%8e%e3%83%bc%e3%83%96%e3%83%ac%e3%83%bc%e3%82%ad%e3%81%ae%e3%82%aa%e3%83%aa%e3%82%b8%e3%83%b3%e3%82%a2%e3%83%af%e3%83%bc"
  },
  {
   "date": "2014-04-08",
   "title": "140408ノーブレーキのオリジンアワー",
   "page": "https://www.fmnaha.jp/podcast_audio/140408%e3%83%8e%e3%83%bc%e3%83%96%e3%83%ac%e3%83%bc%e3%82%ad%e3%81%ae%e3%82%aa%e3%83%aa%e3%82%b8%e3%83%b3%e3%82%a2%e3%83%af%e3%83%bc"
  },
  {
   "date": "2014-04-15",
   "title": "140415ノーブレーキのオリジンアワー",
   "page": "https://www.fmnaha.jp/podcast_audio/140415%e3%83%8e%e3%83%bc%e3%83%96%e3%83%ac%e3%83%bc%e3%82%ad%e3%81%ae%e3%82%aa%e3%83%aa%e3%82%b8%e3%83%b3%e3%82%a2%e3%83%af%e3%83%bc"
  },
  {
   "date": "2014-04-22",
   "title": "140422ノーブレーキのオリジンアワー",
   "page": "https://www.fmnaha.jp/podcast_audio/140422%e3%83%8e%e3%83%bc%e3%83%96%e3%83%ac%e3%83%bc%e3%82%ad%e3%81%ae%e3%82%aa%e3%83%aa%e3%82%b8%e3%83%b3%e3%82%a2%e3%83%af%e3%83%bc"
  },
  {
   "date": "2014-04-29",
   "title": "140429ノーブレーキのオリジンアワー",
   "page": "https://www.fmnaha.jp/podcast_audio/140429%e3%83%8e%e3%83%bc%e3%83%96%e3%83%ac%e3%83%bc%e3%82%ad%e3%81%ae%e3%82%aa%e3%83%aa%e3%82%b8%e3%83%b3%e3%82%a2%e3%83%af%e3%83%bc"
  },
  {
   "date": "2014-05-06",
   "title": "140506ノーブレーキのオリジンアワー",
   "page": "https://www.fmnaha.jp/podcast_audio/140506%e3%83%8e%e3%83%bc%e3%83%96%e3%83%ac%e3%83%bc%e3%82%ad%e3%81%ae%e3%82%aa%e3%83%aa%e3%82%b8%e3%83%b3%e3%82%a2%e3%83%af%e3%83%bc"
  },
  {
   "date": "2014-05-13",
   "title": "140513ノーブレーキのオリジンアワー",
   "page": "https://www.fmnaha.jp/podcast_audio/140513%e3%83%8e%e3%83%bc%e3%83%96%e3%83%ac%e3%83%bc%e3%82%ad%e3%81%ae%e3%82%aa%e3%83%aa%e3%82%b8%e3%83%b3%e3%82%a2%e3%83%af%e3%83%bc"
  },
  {
   "date": "2014-05-20",
   "title": "140520ノーブレーキのオリジンアワー",
   "page": "https://www.fmnaha.jp/podcast_audio/140520%e3%83%8e%e3%83%bc%e3%83%96%e3%83%ac%e3%83%bc%e3%82%ad%e3%81%ae%e3%82%aa%e3%83%aa%e3%82%b8%e3%83%b3%e3%82%a2%e3%83%af%e3%83%bc"
  },
  {
   "date": "2014-05-27",
   "title": "140527ノーブレーキのオリジンアワー",
   "page": "https://www.fmnaha.jp/podcast_audio/140527%e3%83%8e%e3%83%bc%e3%83%96%e3%83%ac%e3%83%bc%e3%82%ad%e3%81%ae%e3%82%aa%e3%83%aa%e3%82%b8%e3%83%b3%e3%82%a2%e3%83%af%e3%83%bc"
  },
  {
   "date": "2014-06-03",
   "title": "140603ノーブレーキのオリジンアワー",
   "page": "https://www.fmnaha.jp/podcast_audio/140603%e3%83%8e%e3%83%bc%e3%83%96%e3%83%ac%e3%83%bc%e3%82%ad%e3%81%ae%e3%82%aa%e3%83%aa%e3%82%b8%e3%83%b3%e3%82%a2%e3%83%af%e3%83%bc"
  },
  {
   "date": "2014-06-10",
   "title": "140610ノーブレーキのオリジンアワー",
   "page": "https://www.fmnaha.jp/podcast_audio/140610%e3%83%8e%e3%83%bc%e3%83%96%e3%83%ac%e3%83%bc%e3%82%ad%e3%81%ae%e3%82%aa%e3%83%aa%e3%82%b8%e3%83%b3%e3%82%a2%e3%83%af%e3%83%bc"
  },
  {
   "date": "2014-06-17",
   "title": "140617ノーブレーキのオリジンアワー",
   "page": "https://www.fmnaha.jp/podcast_audio/140617%e3%83%8e%e3%83%bc%e3%83%96%e3%83%ac%e3%83%bc%e3%82%ad%e3%81%ae%e3%82%aa%e3%83%aa%e3%82%b8%e3%83%b3%e3%82%a2%e3%83%af%e3%83%bc"
  },
  {
   "date": "2014-07-15",
   "title": "140715ノーブレーキのオリジンアワー",
   "page": "https://www.fmnaha.jp/podcast_audio/140715%e3%83%8e%e3%83%bc%e3%83%96%e3%83%ac%e3%83%bc%e3%82%ad%e3%81%ae%e3%82%aa%e3%83%aa%e3%82%b8%e3%83%b3%e3%82%a2%e3%83%af%e3%83%bc"
  },
  {
   "date": "2014-07-22",
   "title": "140722ノーブレーキのオリジンアワー",
   "page": "https://www.fmnaha.jp/podcast_audio/140722%e3%83%8e%e3%83%bc%e3%83%96%e3%83%ac%e3%83%bc%e3%82%ad%e3%81%ae%e3%82%aa%e3%83%aa%e3%82%b8%e3%83%b3%e3%82%a2%e3%83%af%e3%83%bc"
  },
  {
   "date": "2014-07-29",
   "title": "140729ノーブレーキのオリジンアワー",
   "page": "https://www.fmnaha.jp/podcast_audio/140729%e3%83%8e%e3%83%bc%e3%83%96%e3%83%ac%e3%83%bc%e3%82%ad%e3%81%ae%e3%82%aa%e3%83%aa%e3%82%b8%e3%83%b3%e3%82%a2%e3%83%af%e3%83%bc"
  },
  {
   "date": "2014-08-05",
   "title": "140805ノーブレーキのオリジンアワー",
   "page": "https://www.fmnaha.jp/podcast_audio/140805%e3%83%8e%e3%83%bc%e3%83%96%e3%83%ac%e3%83%bc%e3%82%ad%e3%81%ae%e3%82%aa%e3%83%aa%e3%82%b8%e3%83%b3%e3%82%a2%e3%83%af%e3%83%bc"
  },
  {
   "date": "2014-08-12",
   "title": "140812ノーブレーキのオリジンアワー",
   "page": "https://www.fmnaha.jp/podcast_audio/140812%e3%83%8e%e3%83%bc%e3%83%96%e3%83%ac%e3%83%bc%e3%82%ad%e3%81%ae%e3%82%aa%e3%83%aa%e3%82%b8%e3%83%b3%e3%82%a2%e3%83%af%e3%83%bc"
  },
  {
   "date": "2014-08-19",
   "title": "140819ノーブレーキのオリジンアワー",
   "page": "https://www.fmnaha.jp/podcast_audio/140819%e3%83%8e%e3%83%bc%e3%83%96%e3%83%ac%e3%83%bc%e3%82%ad%e3%81%ae%e3%82%aa%e3%83%aa%e3%82%b8%e3%83%b3%e3%82%a2%e3%83%af%e3%83%bc"
  },
  {
   "date": "2014-08-26",
   "title": "140826ノーブレーキのオリジンアワー",
   "page": "https://www.fmnaha.jp/podcast_audio/140826%e3%83%8e%e3%83%bc%e3%83%96%e3%83%ac%e3%83%bc%e3%82%ad%e3%81%ae%e3%82%aa%e3%83%aa%e3%82%b8%e3%83%b3%e3%82%a2%e3%83%af%e3%83%bc"
  },
  {
   "date": "2014-09-02",
   "title": "140902ノーブレーキのオリジンアワー",
   "page": "https://www.fmnaha.jp/podcast_audio/140902%e3%83%8e%e3%83%bc%e3%83%96%e3%83%ac%e3%83%bc%e3%82%ad%e3%81%ae%e3%82%aa%e3%83%aa%e3%82%b8%e3%83%b3%e3%82%a2%e3%83%af%e3%83%bc"
  },
  {
   "date": "2014-09-09",
   "title": "140909ノーブレーキのオリジンアワー",
   "page": "https://www.fmnaha.jp/podcast_audio/140909%e3%83%8e%e3%83%bc%e3%83%96%e3%83%ac%e3%83%bc%e3%82%ad%e3%81%ae%e3%82%aa%e3%83%aa%e3%82%b8%e3%83%b3%e3%82%a2%e3%83%af%e3%83%bc"
  },
  {
   "date": "2014-09-16",
   "title": "140916ノーブレーキのオリジンアワー",
   "page": "https://www.fmnaha.jp/podcast_audio/140916%e3%83%8e%e3%83%bc%e3%83%96%e3%83%ac%e3%83%bc%e3%82%ad%e3%81%ae%e3%82%aa%e3%83%aa%e3%82%b8%e3%83%b3%e3%82%a2%e3%83%af%e3%83%bc"
  },
  {
   "date": "2014-09-23",
   "title": "140923ノーブレーキのオリジンアワー",
   "page": "https://www.fmnaha.jp/podcast_audio/140923%e3%83%8e%e3%83%bc%e3%83%96%e3%83%ac%e3%83%bc%e3%82%ad%e3%81%ae%e3%82%aa%e3%83%aa%e3%82%b8%e3%83%b3%e3%82%a2%e3%83%af%e3%83%bc"
  },
  {
   "date": "2014-09-30",
   "title": "140930ノーブレーキのオリジンアワー",
   "page": "https://www.fmnaha.jp/podcast_audio/140930%e3%83%8e%e3%83%bc%e3%83%96%e3%83%ac%e3%83%bc%e3%82%ad%e3%81%ae%e3%82%aa%e3%83%aa%e3%82%b8%e3%83%b3%e3%82%a2%e3%83%af%e3%83%bc"
  },
  {
   "date": "2014-10-07",
   "title": "141007ノーブレーキのオリジンアワー",
   "page": "https://www.fmnaha.jp/podcast_audio/141007%e3%83%8e%e3%83%bc%e3%83%96%e3%83%ac%e3%83%bc%e3%82%ad%e3%81%ae%e3%82%aa%e3%83%aa%e3%82%b8%e3%83%b3%e3%82%a2%e3%83%af%e3%83%bc"
  },
  {
   "date": "2014-10-14",
   "title": "141014ノーブレーキのオリジンアワー",
   "page": "https://www.fmnaha.jp/podcast_audio/141014%e3%83%8e%e3%83%bc%e3%83%96%e3%83%ac%e3%83%bc%e3%82%ad%e3%81%ae%e3%82%aa%e3%83%aa%e3%82%b8%e3%83%b3%e3%82%a2%e3%83%af%e3%83%bc"
  },
  {
   "date": "2014-10-21",
   "title": "141021ノーブレーキのオリジンアワー",
   "page": "https://www.fmnaha.jp/podcast_audio/141021%e3%83%8e%e3%83%bc%e3%83%96%e3%83%ac%e3%83%bc%e3%82%ad%e3%81%ae%e3%82%aa%e3%83%aa%e3%82%b8%e3%83%b3%e3%82%a2%e3%83%af%e3%83%bc"
  },
  {
   "date": "2014-10-28",
   "title": "141028ノーブレーキのオリジンアワー",
   "page": "https://www.fmnaha.jp/podcast_audio/141028%e3%83%8e%e3%83%bc%e3%83%96%e3%83%ac%e3%83%bc%e3%82%ad%e3%81%ae%e3%82%aa%e3%83%aa%e3%82%b8%e3%83%b3%e3%82%a2%e3%83%af%e3%83%bc"
  },
  {
   "date": "2014-11-04",
   "title": "141104ノーブレーキのオリジンアワー",
   "page": "https://www.fmnaha.jp/podcast_audio/141104%e3%83%8e%e3%83%bc%e3%83%96%e3%83%ac%e3%83%bc%e3%82%ad%e3%81%ae%e3%82%aa%e3%83%aa%e3%82%b8%e3%83%b3%e3%82%a2%e3%83%af%e3%83%bc"
  },
  {
   "date": "2014-11-11",
   "title": "141111ノーブレーキのオリジンアワー",
   "page": "https://www.fmnaha.jp/podcast_audio/141111%e3%83%8e%e3%83%bc%e3%83%96%e3%83%ac%e3%83%bc%e3%82%ad%e3%81%ae%e3%82%aa%e3%83%aa%e3%82%b8%e3%83%b3%e3%82%a2%e3%83%af%e3%83%bc"
  },
  {
   "date": "2014-11-18",
   "title": "141118ノーブレーキのオリジンアワー",
   "page": "https://www.fmnaha.jp/podcast_audio/141118%e3%83%8e%e3%83%bc%e3%83%96%e3%83%ac%e3%83%bc%e3%82%ad%e3%81%ae%e3%82%aa%e3%83%aa%e3%82%b8%e3%83%b3%e3%82%a2%e3%83%af%e3%83%bc"
  },
  {
   "date": "2014-11-25",
   "title": "141125ノーブレーキのオリジンアワー",
   "page": "https://www.fmnaha.jp/podcast_audio/141125%e3%83%8e%e3%83%bc%e3%83%96%e3%83%ac%e3%83%bc%e3%82%ad%e3%81%ae%e3%82%aa%e3%83%aa%e3%82%b8%e3%83%b3%e3%82%a2%e3%83%af%e3%83%bc"
  },
  {
   "date": "2014-12-02",
   "title": "141202ノーブレーキのオリジンアワー",
   "page": "https://www.fmnaha.jp/podcast_audio/141202%e3%83%8e%e3%83%bc%e3%83%96%e3%83%ac%e3%83%bc%e3%82%ad%e3%81%ae%e3%82%aa%e3%83%aa%e3%82%b8%e3%83%b3%e3%82%a2%e3%83%af%e3%83%bc"
  },
  {
   "date": "2014-12-09",
   "title": "141209ノーブレーキのオリジンアワー",
   "page": "https://www.fmnaha.jp/podcast_audio/141209%e3%83%8e%e3%83%bc%e3%83%96%e3%83%ac%e3%83%bc%e3%82%ad%e3%81%ae%e3%82%aa%e3%83%aa%e3%82%b8%e3%83%b3%e3%82%a2%e3%83%af%e3%83%bc"
  },
  {
   "date": "2014-12-16",
   "title": "141216ノーブレーキのオリジンアワー",
   "page": "https://www.fmnaha.jp/podcast_audio/141216%e3%83%8e%e3%83%bc%e3%83%96%e3%83%ac%e3%83%bc%e3%82%ad%e3%81%ae%e3%82%aa%e3%83%aa%e3%82%b8%e3%83%b3%e3%82%a2%e3%83%af%e3%83%bc"
  },
  {
   "date": "2014-12-23",
   "title": "141223ノーブレーキのオリジンアワー",
   "page": "https://www.fmnaha.jp/podcast_audio/141223%e3%83%8e%e3%83%bc%e3%83%96%e3%83%ac%e3%83%bc%e3%82%ad%e3%81%ae%e3%82%aa%e3%83%aa%e3%82%b8%e3%83%b3%e3%82%a2%e3%83%af%e3%83%bc"
  },
  {
   "date": "2015-01-06",
   "title": "150106ノーブレーキのオリジンアワー",
   "page": "https://www.fmnaha.jp/podcast_audio/150106%e3%83%8e%e3%83%bc%e3%83%96%e3%83%ac%e3%83%bc%e3%82%ad%e3%81%ae%e3%82%aa%e3%83%aa%e3%82%b8%e3%83%b3%e3%82%a2%e3%83%af%e3%83%bc"
  },
  {
   "date": "2015-01-13",
   "title": "150113ノーブレーキのオリジンアワー",
   "page": "https://www.fmnaha.jp/podcast_audio/150113%e3%83%8e%e3%83%bc%e3%83%96%e3%83%ac%e3%83%bc%e3%82%ad%e3%81%ae%e3%82%aa%e3%83%aa%e3%82%b8%e3%83%b3%e3%82%a2%e3%83%af%e3%83%bc"
  },
  {
   "date": "2015-01-20",
   "title": "150120ノーブレーキのオリジンアワー",
   "page": "https://www.fmnaha.jp/podcast_audio/150120%e3%83%8e%e3%83%bc%e3%83%96%e3%83%ac%e3%83%bc%e3%82%ad%e3%81%ae%e3%82%aa%e3%83%aa%e3%82%b8%e3%83%b3%e3%82%a2%e3%83%af%e3%83%bc"
  },
  {
   "date": "2015-01-27",
   "title": "150127ノーブレーキのオリジンアワー",
   "page": "https://www.fmnaha.jp/podcast_audio/150127%e3%83%8e%e3%83%bc%e3%83%96%e3%83%ac%e3%83%bc%e3%82%ad%e3%81%ae%e3%82%aa%e3%83%aa%e3%82%b8%e3%83%b3%e3%82%a2%e3%83%af%e3%83%bc"
  },
  {
   "date": "2015-02-03",
   "title": "150203ノーブレーキのオリジンアワー",
   "page": "https://www.fmnaha.jp/podcast_audio/150203%e3%83%8e%e3%83%bc%e3%83%96%e3%83%ac%e3%83%bc%e3%82%ad%e3%81%ae%e3%82%aa%e3%83%aa%e3%82%b8%e3%83%b3%e3%82%a2%e3%83%af%e3%83%bc"
  },
  {
   "date": "2015-02-10",
   "title": "150210ノーブレーキのオリジンアワー",
   "page": "https://www.fmnaha.jp/podcast_audio/150210%e3%83%8e%e3%83%bc%e3%83%96%e3%83%ac%e3%83%bc%e3%82%ad%e3%81%ae%e3%82%aa%e3%83%aa%e3%82%b8%e3%83%b3%e3%82%a2%e3%83%af%e3%83%bc"
  },
  {
   "date": "2015-02-17",
   "title": "150217ノーブレーキのオリジンアワー",
   "page": "https://www.fmnaha.jp/podcast_audio/150217%e3%83%8e%e3%83%bc%e3%83%96%e3%83%ac%e3%83%bc%e3%82%ad%e3%81%ae%e3%82%aa%e3%83%aa%e3%82%b8%e3%83%b3%e3%82%a2%e3%83%af%e3%83%bc"
  },
  {
   "date": "2015-02-24",
   "title": "150224ノーブレーキのオリジンアワー",
   "page": "https://www.fmnaha.jp/podcast_audio/150224%e3%83%8e%e3%83%bc%e3%83%96%e3%83%ac%e3%83%bc%e3%82%ad%e3%81%ae%e3%82%aa%e3%83%aa%e3%82%b8%e3%83%b3%e3%82%a2%e3%83%af%e3%83%bc"
  },
  {
   "date": "2015-03-03",
   "title": "150303ノーブレーキのオリジンアワー",
   "page": "https://www.fmnaha.jp/podcast_audio/150303%e3%83%8e%e3%83%bc%e3%83%96%e3%83%ac%e3%83%bc%e3%82%ad%e3%81%ae%e3%82%aa%e3%83%aa%e3%82%b8%e3%83%b3%e3%82%a2%e3%83%af%e3%83%bc"
  },
  {
   "date": "2015-03-10",
   "title": "150310ノーブレーキのオリジンアワー",
   "page": "https://www.fmnaha.jp/podcast_audio/150310%e3%83%8e%e3%83%bc%e3%83%96%e3%83%ac%e3%83%bc%e3%82%ad%e3%81%ae%e3%82%aa%e3%83%aa%e3%82%b8%e3%83%b3%e3%82%a2%e3%83%af%e3%83%bc"
  },
  {
   "date": "2015-03-17",
   "title": "150317ノーブレーキのオリジンアワー",
   "page": "https://www.fmnaha.jp/podcast_audio/150317%e3%83%8e%e3%83%bc%e3%83%96%e3%83%ac%e3%83%bc%e3%82%ad%e3%81%ae%e3%82%aa%e3%83%aa%e3%82%b8%e3%83%b3%e3%82%a2%e3%83%af%e3%83%bc"
  },
  {
   "date": "2015-03-24",
   "title": "150324ノーブレーキのオリジンアワー",
   "page": "https://www.fmnaha.jp/podcast_audio/150324%e3%83%8e%e3%83%bc%e3%83%96%e3%83%ac%e3%83%bc%e3%82%ad%e3%81%ae%e3%82%aa%e3%83%aa%e3%82%b8%e3%83%b3%e3%82%a2%e3%83%af%e3%83%bc"
  },
  {
   "date": "2015-03-31",
   "title": "150331ノーブレーキのオリジンアワー",
   "page": "https://www.fmnaha.jp/podcast_audio/150331%e3%83%8e%e3%83%bc%e3%83%96%e3%83%ac%e3%83%bc%e3%82%ad%e3%81%ae%e3%82%aa%e3%83%aa%e3%82%b8%e3%83%b3%e3%82%a2%e3%83%af%e3%83%bc"
  },
  {
   "date": "2015-04-07",
   "title": "150407ノーブレーキのオリジンアワー",
   "page": "https://www.fmnaha.jp/podcast_audio/150407%e3%83%8e%e3%83%bc%e3%83%96%e3%83%ac%e3%83%bc%e3%82%ad%e3%81%ae%e3%82%aa%e3%83%aa%e3%82%b8%e3%83%b3%e3%82%a2%e3%83%af%e3%83%bc"
  },
  {
   "date": "2015-04-14",
   "title": "150414ノーブレーキのオリジンアワー",
   "page": "https://www.fmnaha.jp/podcast_audio/150414%e3%83%8e%e3%83%bc%e3%83%96%e3%83%ac%e3%83%bc%e3%82%ad%e3%81%ae%e3%82%aa%e3%83%aa%e3%82%b8%e3%83%b3%e3%82%a2%e3%83%af%e3%83%bc"
  },
  {
   "date": "2015-04-21",
   "title": "150421ノーブレーキのオリジンアワー",
   "page": "https://www.fmnaha.jp/podcast_audio/150421%e3%83%8e%e3%83%bc%e3%83%96%e3%83%ac%e3%83%bc%e3%82%ad%e3%81%ae%e3%82%aa%e3%83%aa%e3%82%b8%e3%83%b3%e3%82%a2%e3%83%af%e3%83%bc"
  },
  {
   "date": "2015-04-28",
   "title": "150428ノーブレーキのオリジンアワー",
   "page": "https://www.fmnaha.jp/podcast_audio/150428%e3%83%8e%e3%83%bc%e3%83%96%e3%83%ac%e3%83%bc%e3%82%ad%e3%81%ae%e3%82%aa%e3%83%aa%e3%82%b8%e3%83%b3%e3%82%a2%e3%83%af%e3%83%bc"
  },
  {
   "date": "2015-05-05",
   "title": "150505ノーブレーキのオリジンアワー",
   "page": "https://www.fmnaha.jp/podcast_audio/150505%e3%83%8e%e3%83%bc%e3%83%96%e3%83%ac%e3%83%bc%e3%82%ad%e3%81%ae%e3%82%aa%e3%83%aa%e3%82%b8%e3%83%b3%e3%82%a2%e3%83%af%e3%83%bc"
  },
  {
   "date": "2015-05-12",
   "title": "150512ノーブレーキのオリジンアワー",
   "page": "https://www.fmnaha.jp/podcast_audio/150512%e3%83%8e%e3%83%bc%e3%83%96%e3%83%ac%e3%83%bc%e3%82%ad%e3%81%ae%e3%82%aa%e3%83%aa%e3%82%b8%e3%83%b3%e3%82%a2%e3%83%af%e3%83%bc"
  },
  {
   "date": "2015-05-19",
   "title": "150519ノーブレーキのオリジンアワー",
   "page": "https://www.fmnaha.jp/podcast_audio/150519%e3%83%8e%e3%83%bc%e3%83%96%e3%83%ac%e3%83%bc%e3%82%ad%e3%81%ae%e3%82%aa%e3%83%aa%e3%82%b8%e3%83%b3%e3%82%a2%e3%83%af%e3%83%bc"
  },
  {
   "date": "2015-08-04",
   "title": "150804ノーブレーキのオリジンアワー",
   "page": "https://www.fmnaha.jp/podcast_audio/150804%e3%83%8e%e3%83%bc%e3%83%96%e3%83%ac%e3%83%bc%e3%82%ad%e3%81%ae%e3%82%aa%e3%83%aa%e3%82%b8%e3%83%b3%e3%82%a2%e3%83%af%e3%83%bc"
  },
  {
   "date": "2015-08-11",
   "title": "150811ノーブレーキのオリジンアワー",
   "page": "https://www.fmnaha.jp/podcast_audio/150811%e3%83%8e%e3%83%bc%e3%83%96%e3%83%ac%e3%83%bc%e3%82%ad%e3%81%ae%e3%82%aa%e3%83%aa%e3%82%b8%e3%83%b3%e3%82%a2%e3%83%af%e3%83%bc"
  },
  {
   "date": "2015-08-18",
   "title": "150818ノーブレーキのオリジンアワー",
   "page": "https://www.fmnaha.jp/podcast_audio/150818%e3%83%8e%e3%83%bc%e3%83%96%e3%83%ac%e3%83%bc%e3%82%ad%e3%81%ae%e3%82%aa%e3%83%aa%e3%82%b8%e3%83%b3%e3%82%a2%e3%83%af%e3%83%bc"
  },
  {
   "date": "2015-08-25",
   "title": "150825ノーブレーキのオリジンアワー",
   "page": "https://www.fmnaha.jp/podcast_audio/150825%e3%83%8e%e3%83%bc%e3%83%96%e3%83%ac%e3%83%bc%e3%82%ad%e3%81%ae%e3%82%aa%e3%83%aa%e3%82%b8%e3%83%b3%e3%82%a2%e3%83%af%e3%83%bc"
  },
  {
   "date": "2015-09-01",
   "title": "150901ノーブレーキのオリジンアワー",
   "page": "https://www.fmnaha.jp/podcast_audio/150901%e3%83%8e%e3%83%bc%e3%83%96%e3%83%ac%e3%83%bc%e3%82%ad%e3%81%ae%e3%82%aa%e3%83%aa%e3%82%b8%e3%83%b3%e3%82%a2%e3%83%af%e3%83%bc"
  },
  {
   "date": "2015-09-08",
   "title": "150908ノーブレーキのオリジンアワー",
   "page": "https://www.fmnaha.jp/podcast_audio/150908%e3%83%8e%e3%83%bc%e3%83%96%e3%83%ac%e3%83%bc%e3%82%ad%e3%81%ae%e3%82%aa%e3%83%aa%e3%82%b8%e3%83%b3%e3%82%a2%e3%83%af%e3%83%bc"
  },
  {
   "date": "2015-09-15",
   "title": "150915ノーブレーキのオリジンアワー",
   "page": "https://www.fmnaha.jp/podcast_audio/150915%e3%83%8e%e3%83%bc%e3%83%96%e3%83%ac%e3%83%bc%e3%82%ad%e3%81%ae%e3%82%aa%e3%83%aa%e3%82%b8%e3%83%b3%e3%82%a2%e3%83%af%e3%83%bc"
  },
  {
   "date": "2015-09-22",
   "title": "150922【当】ノーブレーキのオリジンアワー",
   "page": "https://www.fmnaha.jp/podcast_audio/150922%e3%80%90%e5%bd%93%e3%80%91%e3%83%8e%e3%83%bc%e3%83%96%e3%83%ac%e3%83%bc%e3%82%ad%e3%81%ae%e3%82%aa%e3%83%aa%e3%82%b8%e3%83%b3%e3%82%a2%e3%83%af%e3%83%bc"
  },
  {
   "date": "2015-09-29",
   "title": "150929ノーブレーキのオリジンアワー",
   "page": "https://www.fmnaha.jp/podcast_audio/150929%e3%83%8e%e3%83%bc%e3%83%96%e3%83%ac%e3%83%bc%e3%82%ad%e3%81%ae%e3%82%aa%e3%83%aa%e3%82%b8%e3%83%b3%e3%82%a2%e3%83%af%e3%83%bc"
  },
  {
   "date": "2015-10-06",
   "title": "151006ノーブレーキのオリジンアワー",
   "page": "https://www.fmnaha.jp/podcast_audio/151006%e3%83%8e%e3%83%bc%e3%83%96%e3%83%ac%e3%83%bc%e3%82%ad%e3%81%ae%e3%82%aa%e3%83%aa%e3%82%b8%e3%83%b3%e3%82%a2%e3%83%af%e3%83%bc"
  },
  {
   "date": "2015-10-13",
   "title": "151013ノーブレーキのオリジンアワー",
   "page": "https://www.fmnaha.jp/podcast_audio/151013%e3%83%8e%e3%83%bc%e3%83%96%e3%83%ac%e3%83%bc%e3%82%ad%e3%81%ae%e3%82%aa%e3%83%aa%e3%82%b8%e3%83%b3%e3%82%a2%e3%83%af%e3%83%bc"
  },
  {
   "date": "2015-10-20",
   "title": "151020ノーブレーキのオリジンアワー",
   "page": "https://www.fmnaha.jp/podcast_audio/151020%e3%83%8e%e3%83%bc%e3%83%96%e3%83%ac%e3%83%bc%e3%82%ad%e3%81%ae%e3%82%aa%e3%83%aa%e3%82%b8%e3%83%b3%e3%82%a2%e3%83%af%e3%83%bc"
  },
  {
   "date": "2015-10-27",
   "title": "151027ノーブレーキのオリジンアワー",
   "page": "https://www.fmnaha.jp/podcast_audio/151027%e3%83%8e%e3%83%bc%e3%83%96%e3%83%ac%e3%83%bc%e3%82%ad%e3%81%ae%e3%82%aa%e3%83%aa%e3%82%b8%e3%83%b3%e3%82%a2%e3%83%af%e3%83%bc"
  },
  {
   "date": "2015-11-03",
   "title": "151103ノーブレーキのオリジンアワー",
   "page": "https://www.fmnaha.jp/podcast_audio/151103%e3%83%8e%e3%83%bc%e3%83%96%e3%83%ac%e3%83%bc%e3%82%ad%e3%81%ae%e3%82%aa%e3%83%aa%e3%82%b8%e3%83%b3%e3%82%a2%e3%83%af%e3%83%bc"
  },
  {
   "date": "2015-11-10",
   "title": "151110ノーブレーキのオリジンアワー",
   "page": "https://www.fmnaha.jp/podcast_audio/151110%e3%83%8e%e3%83%bc%e3%83%96%e3%83%ac%e3%83%bc%e3%82%ad%e3%81%ae%e3%82%aa%e3%83%aa%e3%82%b8%e3%83%b3%e3%82%a2%e3%83%af%e3%83%bc"
  },
  {
   "date": "2015-11-17",
   "title": "151117ノーブレーキのオリジンアワー",
   "page": "https://www.fmnaha.jp/podcast_audio/151117%e3%83%8e%e3%83%bc%e3%83%96%e3%83%ac%e3%83%bc%e3%82%ad%e3%81%ae%e3%82%aa%e3%83%aa%e3%82%b8%e3%83%b3%e3%82%a2%e3%83%af%e3%83%bc"
  },
  {
   "date": "2015-11-24",
   "title": "151124ノーブレーキのオリジンアワー",
   "page": "https://www.fmnaha.jp/podcast_audio/151124%e3%83%8e%e3%83%bc%e3%83%96%e3%83%ac%e3%83%bc%e3%82%ad%e3%81%ae%e3%82%aa%e3%83%aa%e3%82%b8%e3%83%b3%e3%82%a2%e3%83%af%e3%83%bc"
  },
  {
   "date": "2015-12-01",
   "title": "151201ノーブレーキのオリジンアワー",
   "page": "https://www.fmnaha.jp/podcast_audio/151201%e3%83%8e%e3%83%bc%e3%83%96%e3%83%ac%e3%83%bc%e3%82%ad%e3%81%ae%e3%82%aa%e3%83%aa%e3%82%b8%e3%83%b3%e3%82%a2%e3%83%af%e3%83%bc"
  },
  {
   "date": "2015-12-08",
   "title": "151208ノーブレーキのオリジンアワー",
   "page": "https://www.fmnaha.jp/podcast_audio/151208%e3%83%8e%e3%83%bc%e3%83%96%e3%83%ac%e3%83%bc%e3%82%ad%e3%81%ae%e3%82%aa%e3%83%aa%e3%82%b8%e3%83%b3%e3%82%a2%e3%83%af%e3%83%bc"
  },
  {
   "date": "2015-12-15",
   "title": "151215ノーブレーキのオリジンアワー",
   "page": "https://www.fmnaha.jp/podcast_audio/151215%e3%83%8e%e3%83%bc%e3%83%96%e3%83%ac%e3%83%bc%e3%82%ad%e3%81%ae%e3%82%aa%e3%83%aa%e3%82%b8%e3%83%b3%e3%82%a2%e3%83%af%e3%83%bc"
  },
  {
   "date": "2015-12-22",
   "title": "151222ノーブレーキのオリジンアワー",
   "page": "https://www.fmnaha.jp/podcast_audio/151222%e3%83%8e%e3%83%bc%e3%83%96%e3%83%ac%e3%83%bc%e3%82%ad%e3%81%ae%e3%82%aa%e3%83%aa%e3%82%b8%e3%83%b3%e3%82%a2%e3%83%af%e3%83%bc"
  },
  {
   "date": "2016-01-05",
   "title": "160105ノーブレーキのオリジンアワー",
   "page": "https://www.fmnaha.jp/podcast_audio/160105%e3%83%8e%e3%83%bc%e3%83%96%e3%83%ac%e3%83%bc%e3%82%ad%e3%81%ae%e3%82%aa%e3%83%aa%e3%82%b8%e3%83%b3%e3%82%a2%e3%83%af%e3%83%bc"
  },
  {
   "date": "2016-01-12",
   "title": "160112ノーブレーキのオリジンアワー",
   "page": "https://www.fmnaha.jp/podcast_audio/160112%e3%83%8e%e3%83%bc%e3%83%96%e3%83%ac%e3%83%bc%e3%82%ad%e3%81%ae%e3%82%aa%e3%83%aa%e3%82%b8%e3%83%b3%e3%82%a2%e3%83%af%e3%83%bc"
  },
  {
   "date": "2016-01-19",
   "title": "160119ノーブレーキのオリジンアワー",
   "page": "https://www.fmnaha.jp/podcast_audio/160119%e3%83%8e%e3%83%bc%e3%83%96%e3%83%ac%e3%83%bc%e3%82%ad%e3%81%ae%e3%82%aa%e3%83%aa%e3%82%b8%e3%83%b3%e3%82%a2%e3%83%af%e3%83%bc"
  },
  {
   "date": "2016-01-26",
   "title": "160126ノーブレーキのオリジンアワー",
   "page": "https://www.fmnaha.jp/podcast_audio/160126%e3%83%8e%e3%83%bc%e3%83%96%e3%83%ac%e3%83%bc%e3%82%ad%e3%81%ae%e3%82%aa%e3%83%aa%e3%82%b8%e3%83%b3%e3%82%a2%e3%83%af%e3%83%bc"
  },
  {
   "date": "2016-02-02",
   "title": "160202ノーブレーキのオリジンアワー",
   "page": "https://www.fmnaha.jp/podcast_audio/160202%e3%83%8e%e3%83%bc%e3%83%96%e3%83%ac%e3%83%bc%e3%82%ad%e3%81%ae%e3%82%aa%e3%83%aa%e3%82%b8%e3%83%b3%e3%82%a2%e3%83%af%e3%83%bc"
  },
  {
   "date": "2016-02-09",
   "title": "160209ノーブレーキのオリジンアワー公開収録-in-ハル晴",
   "page": "https://www.fmnaha.jp/podcast_audio/160209%e3%83%8e%e3%83%bc%e3%83%96%e3%83%ac%e3%83%bc%e3%82%ad%e3%81%ae%e3%82%aa%e3%83%aa%e3%82%b8%e3%83%b3%e3%82%a2%e3%83%af%e3%83%bc%e5%85%ac%e9%96%8b%e5%8f%8e%e9%8c%b2-in-%e3%83%8f%e3%83%ab%e6%99%b4"
  },
  {
   "date": "2016-02-16",
   "title": "160216ノーブレーキのオリジンアワー",
   "page": "https://www.fmnaha.jp/podcast_audio/160216%e3%83%8e%e3%83%bc%e3%83%96%e3%83%ac%e3%83%bc%e3%82%ad%e3%81%ae%e3%82%aa%e3%83%aa%e3%82%b8%e3%83%b3%e3%82%a2%e3%83%af%e3%83%bc"
  },
  {
   "date": "2016-02-23",
   "title": "160223ノーブレーキのオリジンアワー",
   "page": "https://www.fmnaha.jp/podcast_audio/160223%e3%83%8e%e3%83%bc%e3%83%96%e3%83%ac%e3%83%bc%e3%82%ad%e3%81%ae%e3%82%aa%e3%83%aa%e3%82%b8%e3%83%b3%e3%82%a2%e3%83%af%e3%83%bc"
  },
  {
   "date": "2016-03-01",
   "title": "160301ノーブレーキのオリジンアワー",
   "page": "https://www.fmnaha.jp/podcast_audio/160301%e3%83%8e%e3%83%bc%e3%83%96%e3%83%ac%e3%83%bc%e3%82%ad%e3%81%ae%e3%82%aa%e3%83%aa%e3%82%b8%e3%83%b3%e3%82%a2%e3%83%af%e3%83%bc"
  },
  {
   "date": "2016-03-08",
   "title": "160308ノーブレーキのオリジンアワー",
   "page": "https://www.fmnaha.jp/podcast_audio/160308%e3%83%8e%e3%83%bc%e3%83%96%e3%83%ac%e3%83%bc%e3%82%ad%e3%81%ae%e3%82%aa%e3%83%aa%e3%82%b8%e3%83%b3%e3%82%a2%e3%83%af%e3%83%bc"
  },
  {
   "date": "2016-03-15",
   "title": "160315ノーブレーキのオリジンアワー",
   "page": "https://www.fmnaha.jp/podcast_audio/160315%e3%83%8e%e3%83%bc%e3%83%96%e3%83%ac%e3%83%bc%e3%82%ad%e3%81%ae%e3%82%aa%e3%83%aa%e3%82%b8%e3%83%b3%e3%82%a2%e3%83%af%e3%83%bc"
  },
  {
   "date": "2016-03-22",
   "title": "160322ノーブレーキのオリジンアワー",
   "page": "https://www.fmnaha.jp/podcast_audio/160322%e3%83%8e%e3%83%bc%e3%83%96%e3%83%ac%e3%83%bc%e3%82%ad%e3%81%ae%e3%82%aa%e3%83%aa%e3%82%b8%e3%83%b3%e3%82%a2%e3%83%af%e3%83%bc"
  },
  {
   "date": "2016-03-29",
   "title": "160329ノーブレーキのオリジンアワー",
   "page": "https://www.fmnaha.jp/podcast_audio/160329%e3%83%8e%e3%83%bc%e3%83%96%e3%83%ac%e3%83%bc%e3%82%ad%e3%81%ae%e3%82%aa%e3%83%aa%e3%82%b8%e3%83%b3%e3%82%a2%e3%83%af%e3%83%bc"
  },
  {
   "date": "2016-04-05",
   "title": "160405ノーブレーキのオリジンアワー",
   "page": "https://www.fmnaha.jp/podcast_audio/160405%e3%83%8e%e3%83%bc%e3%83%96%e3%83%ac%e3%83%bc%e3%82%ad%e3%81%ae%e3%82%aa%e3%83%aa%e3%82%b8%e3%83%b3%e3%82%a2%e3%83%af%e3%83%bc"
  },
  {
   "date": "2016-04-12",
   "title": "160412ノーブレーキのオリジンアワー",
   "page": "https://www.fmnaha.jp/podcast_audio/160412%e3%83%8e%e3%83%bc%e3%83%96%e3%83%ac%e3%83%bc%e3%82%ad%e3%81%ae%e3%82%aa%e3%83%aa%e3%82%b8%e3%83%b3%e3%82%a2%e3%83%af%e3%83%bc"
  },
  {
   "date": "2016-04-19",
   "title": "160419ノーブレーキのオリジンアワー",
   "page": "https://www.fmnaha.jp/podcast_audio/160419%e3%83%8e%e3%83%bc%e3%83%96%e3%83%ac%e3%83%bc%e3%82%ad%e3%81%ae%e3%82%aa%e3%83%aa%e3%82%b8%e3%83%b3%e3%82%a2%e3%83%af%e3%83%bc"
  },
  {
   "date": "2016-04-26",
   "title": "160426ノーブレーキのオリジンアワー",
   "page": "https://www.fmnaha.jp/podcast_audio/160426%e3%83%8e%e3%83%bc%e3%83%96%e3%83%ac%e3%83%bc%e3%82%ad%e3%81%ae%e3%82%aa%e3%83%aa%e3%82%b8%e3%83%b3%e3%82%a2%e3%83%af%e3%83%bc"
  },
  {
   "date": "2016-05-03",
   "title": "160503ノーブレーキのオリジンアワー",
   "page": "https://www.fmnaha.jp/podcast_audio/160503%e3%83%8e%e3%83%bc%e3%83%96%e3%83%ac%e3%83%bc%e3%82%ad%e3%81%ae%e3%82%aa%e3%83%aa%e3%82%b8%e3%83%b3%e3%82%a2%e3%83%af%e3%83%bc"
  },
  {
   "date": "2016-05-10",
   "title": "160510ノーブレーキのオリジンアワー",
   "page": "https://www.fmnaha.jp/podcast_audio/160510%e3%83%8e%e3%83%bc%e3%83%96%e3%83%ac%e3%83%bc%e3%82%ad%e3%81%ae%e3%82%aa%e3%83%aa%e3%82%b8%e3%83%b3%e3%82%a2%e3%83%af%e3%83%bc"
  },
  {
   "date": "2016-05-17",
   "title": "160517ノーブレーキのオリジンアワー",
   "page": "https://www.fmnaha.jp/podcast_audio/160517%e3%83%8e%e3%83%bc%e3%83%96%e3%83%ac%e3%83%bc%e3%82%ad%e3%81%ae%e3%82%aa%e3%83%aa%e3%82%b8%e3%83%b3%e3%82%a2%e3%83%af%e3%83%bc"
  },
  {
   "date": "2016-05-24",
   "title": "160524ノーブレーキのオリジンアワー",
   "page": "https://www.fmnaha.jp/podcast_audio/160524%e3%83%8e%e3%83%bc%e3%83%96%e3%83%ac%e3%83%bc%e3%82%ad%e3%81%ae%e3%82%aa%e3%83%aa%e3%82%b8%e3%83%b3%e3%82%a2%e3%83%af%e3%83%bc"
  },
  {
   "date": "2016-05-31",
   "title": "160531ノーブレーキのオリジンアワー",
   "page": "https://www.fmnaha.jp/podcast_audio/160531%e3%83%8e%e3%83%bc%e3%83%96%e3%83%ac%e3%83%bc%e3%82%ad%e3%81%ae%e3%82%aa%e3%83%aa%e3%82%b8%e3%83%b3%e3%82%a2%e3%83%af%e3%83%bc"
  },
  {
   "date": "2016-06-14",
   "title": "160614ノーブレーキのオリジンアワー",
   "page": "https://www.fmnaha.jp/podcast_audio/160614%e3%83%8e%e3%83%bc%e3%83%96%e3%83%ac%e3%83%bc%e3%82%ad%e3%81%ae%e3%82%aa%e3%83%aa%e3%82%b8%e3%83%b3%e3%82%a2%e3%83%af%e3%83%bc"
  },
  {
   "date": "2016-06-21",
   "title": "160621ノーブレーキのオリジンアワー",
   "page": "https://www.fmnaha.jp/podcast_audio/160621%e3%83%8e%e3%83%bc%e3%83%96%e3%83%ac%e3%83%bc%e3%82%ad%e3%81%ae%e3%82%aa%e3%83%aa%e3%82%b8%e3%83%b3%e3%82%a2%e3%83%af%e3%83%bc"
  },
  {
   "date": "2016-06-28",
   "title": "160628ノーブレーキのオリジンアワー",
   "page": "https://www.fmnaha.jp/podcast_audio/160628%e3%83%8e%e3%83%bc%e3%83%96%e3%83%ac%e3%83%bc%e3%82%ad%e3%81%ae%e3%82%aa%e3%83%aa%e3%82%b8%e3%83%b3%e3%82%a2%e3%83%af%e3%83%bc"
  },
  {
   "date": "2016-07-05",
   "title": "160705ノーブレーキのオリジンアワー",
   "page": "https://www.fmnaha.jp/podcast_audio/160705%e3%83%8e%e3%83%bc%e3%83%96%e3%83%ac%e3%83%bc%e3%82%ad%e3%81%ae%e3%82%aa%e3%83%aa%e3%82%b8%e3%83%b3%e3%82%a2%e3%83%af%e3%83%bc"
  },
  {
   "date": "2016-07-12",
   "title": "160712ノーブレーキのオリジンアワー公開収録-in-ハル晴",
   "page": "https://www.fmnaha.jp/podcast_audio/160712%e3%83%8e%e3%83%bc%e3%83%96%e3%83%ac%e3%83%bc%e3%82%ad%e3%81%ae%e3%82%aa%e3%83%aa%e3%82%b8%e3%83%b3%e3%82%a2%e3%83%af%e3%83%bc%e5%85%ac%e9%96%8b%e5%8f%8e%e9%8c%b2-in-%e3%83%8f%e3%83%ab%e6%99%b4"
  },
  {
   "date": "2016-07-19",
   "title": "160719ノーブレーキのオリジンアワー",
   "page": "https://www.fmnaha.jp/podcast_audio/160719%e3%83%8e%e3%83%bc%e3%83%96%e3%83%ac%e3%83%bc%e3%82%ad%e3%81%ae%e3%82%aa%e3%83%aa%e3%82%b8%e3%83%b3%e3%82%a2%e3%83%af%e3%83%bc"
  },
  {
   "date": "2016-07-20",
   "title": "160720ノーブレーキのオリジンアワー",
   "page": "https://www.fmnaha.jp/podcast_audio/160720%e3%83%8e%e3%83%bc%e3%83%96%e3%83%ac%e3%83%bc%e3%82%ad%e3%81%ae%e3%82%aa%e3%83%aa%e3%82%b8%e3%83%b3%e3%82%a2%e3%83%af%e3%83%bc"
  },
  {
   "date": "2016-07-26",
   "title": "160726ノーブレーキのオリジンアワー",
   "page": "https://www.fmnaha.jp/podcast_audio/160726%e3%83%8e%e3%83%bc%e3%83%96%e3%83%ac%e3%83%bc%e3%82%ad%e3%81%ae%e3%82%aa%e3%83%aa%e3%82%b8%e3%83%b3%e3%82%a2%e3%83%af%e3%83%bc"
  },
  {
   "date": "2016-08-02",
   "title": "160802ノーブレーキのオリジンアワー",
   "page": "https://www.fmnaha.jp/podcast_audio/160802%e3%83%8e%e3%83%bc%e3%83%96%e3%83%ac%e3%83%bc%e3%82%ad%e3%81%ae%e3%82%aa%e3%83%aa%e3%82%b8%e3%83%b3%e3%82%a2%e3%83%af%e3%83%bc"
  },
  {
   "date": "2016-08-09",
   "title": "160809ノーブレーキのオリジンアワー",
   "page": "https://www.fmnaha.jp/podcast_audio/160809%e3%83%8e%e3%83%bc%e3%83%96%e3%83%ac%e3%83%bc%e3%82%ad%e3%81%ae%e3%82%aa%e3%83%aa%e3%82%b8%e3%83%b3%e3%82%a2%e3%83%af%e3%83%bc"
  },
  {
   "date": "2016-08-16",
   "title": "160816ノーブレーキのオリジンアワー",
   "page": "https://www.fmnaha.jp/podcast_audio/160816%e3%83%8e%e3%83%bc%e3%83%96%e3%83%ac%e3%83%bc%e3%82%ad%e3%81%ae%e3%82%aa%e3%83%aa%e3%82%b8%e3%83%b3%e3%82%a2%e3%83%af%e3%83%bc"
  },
  {
   "date": "2016-08-23",
   "title": "160823ノーブレーキのオリジンアワー",
   "page": "https://www.fmnaha.jp/podcast_audio/160823%e3%83%8e%e3%83%bc%e3%83%96%e3%83%ac%e3%83%bc%e3%82%ad%e3%81%ae%e3%82%aa%e3%83%aa%e3%82%b8%e3%83%b3%e3%82%a2%e3%83%af%e3%83%bc"
  },
  {
   "date": "2016-08-30",
   "title": "160830ノーブレーキのオリジンアワー",
   "page": "https://www.fmnaha.jp/podcast_audio/160830%e3%83%8e%e3%83%bc%e3%83%96%e3%83%ac%e3%83%bc%e3%82%ad%e3%81%ae%e3%82%aa%e3%83%aa%e3%82%b8%e3%83%b3%e3%82%a2%e3%83%af%e3%83%bc"
  },
  {
   "date": "2016-09-13",
   "title": "160913ノーブレーキのオリジンアワー",
   "page": "https://www.fmnaha.jp/podcast_audio/160913%e3%83%8e%e3%83%bc%e3%83%96%e3%83%ac%e3%83%bc%e3%82%ad%e3%81%ae%e3%82%aa%e3%83%aa%e3%82%b8%e3%83%b3%e3%82%a2%e3%83%af%e3%83%bc"
  },
  {
   "date": "2016-09-20",
   "title": "160920ノーブレーキのオリジンアワー",
   "page": "https://www.fmnaha.jp/podcast_audio/160920%e3%83%8e%e3%83%bc%e3%83%96%e3%83%ac%e3%83%bc%e3%82%ad%e3%81%ae%e3%82%aa%e3%83%aa%e3%82%b8%e3%83%b3%e3%82%a2%e3%83%af%e3%83%bc"
  },
  {
   "date": "2016-09-27",
   "title": "160927ノーブレーキのオリジンアワー",
   "page": "https://www.fmnaha.jp/podcast_audio/160927%e3%83%8e%e3%83%bc%e3%83%96%e3%83%ac%e3%83%bc%e3%82%ad%e3%81%ae%e3%82%aa%e3%83%aa%e3%82%b8%e3%83%b3%e3%82%a2%e3%83%af%e3%83%bc"
  },
  {
   "date": "2016-10-04",
   "title": "161004ノーブレーキのオリジンアワー",
   "page": "https://www.fmnaha.jp/podcast_audio/161004%e3%83%8e%e3%83%bc%e3%83%96%e3%83%ac%e3%83%bc%e3%82%ad%e3%81%ae%e3%82%aa%e3%83%aa%e3%82%b8%e3%83%b3%e3%82%a2%e3%83%af%e3%83%bc"
  },
  {
   "date": "2016-10-11",
   "title": "161011ノーブレーキのオリジンアワー",
   "page": "https://www.fmnaha.jp/podcast_audio/161011%e3%83%8e%e3%83%bc%e3%83%96%e3%83%ac%e3%83%bc%e3%82%ad%e3%81%ae%e3%82%aa%e3%83%aa%e3%82%b8%e3%83%b3%e3%82%a2%e3%83%af%e3%83%bc"
  },
  {
   "date": "2016-10-18",
   "title": "161018ノーブレーキのオリジンアワー",
   "page": "https://www.fmnaha.jp/podcast_audio/161018%e3%83%8e%e3%83%bc%e3%83%96%e3%83%ac%e3%83%bc%e3%82%ad%e3%81%ae%e3%82%aa%e3%83%aa%e3%82%b8%e3%83%b3%e3%82%a2%e3%83%af%e3%83%bc"
  },
  {
   "date": "2016-10-25",
   "title": "161025ノーブレーキのオリジンアワー",
   "page": "https://www.fmnaha.jp/podcast_audio/161025%e3%83%8e%e3%83%bc%e3%83%96%e3%83%ac%e3%83%bc%e3%82%ad%e3%81%ae%e3%82%aa%e3%83%aa%e3%82%b8%e3%83%b3%e3%82%a2%e3%83%af%e3%83%bc"
  },
  {
   "date": "2016-11-08",
   "title": "161108ノーブレーキのオリジンアワー",
   "page": "https://www.fmnaha.jp/podcast_audio/161108%e3%83%8e%e3%83%bc%e3%83%96%e3%83%ac%e3%83%bc%e3%82%ad%e3%81%ae%e3%82%aa%e3%83%aa%e3%82%b8%e3%83%b3%e3%82%a2%e3%83%af%e3%83%bc"
  },
  {
   "date": "2016-11-15",
   "title": "161115ノーブレーキのオリジンアワー",
   "page": "https://www.fmnaha.jp/podcast_audio/161115%e3%83%8e%e3%83%bc%e3%83%96%e3%83%ac%e3%83%bc%e3%82%ad%e3%81%ae%e3%82%aa%e3%83%aa%e3%82%b8%e3%83%b3%e3%82%a2%e3%83%af%e3%83%bc"
  },
  {
   "date": "2016-11-22",
   "title": "161122ノーブレーキのオリジンアワー",
   "page": "https://www.fmnaha.jp/podcast_audio/161122%e3%83%8e%e3%83%bc%e3%83%96%e3%83%ac%e3%83%bc%e3%82%ad%e3%81%ae%e3%82%aa%e3%83%aa%e3%82%b8%e3%83%b3%e3%82%a2%e3%83%af%e3%83%bc"
  },
  {
   "date": "2016-11-29",
   "title": "161129ノーブレーキのオリジンアワー",
   "page": "https://www.fmnaha.jp/podcast_audio/161129%e3%83%8e%e3%83%bc%e3%83%96%e3%83%ac%e3%83%bc%e3%82%ad%e3%81%ae%e3%82%aa%e3%83%aa%e3%82%b8%e3%83%b3%e3%82%a2%e3%83%af%e3%83%bc"
  },
  {
   "date": "2016-12-06",
   "title": "161206ノーブレーキのオリジンアワー",
   "page": "https://www.fmnaha.jp/podcast_audio/161206%e3%83%8e%e3%83%bc%e3%83%96%e3%83%ac%e3%83%bc%e3%82%ad%e3%81%ae%e3%82%aa%e3%83%aa%e3%82%b8%e3%83%b3%e3%82%a2%e3%83%af%e3%83%bc"
  },
  {
   "date": "2016-12-20",
   "title": "161220ノーブレーキのオリジンアワー",
   "page": "https://www.fmnaha.jp/podcast_audio/161220%e3%83%8e%e3%83%bc%e3%83%96%e3%83%ac%e3%83%bc%e3%82%ad%e3%81%ae%e3%82%aa%e3%83%aa%e3%82%b8%e3%83%b3%e3%82%a2%e3%83%af%e3%83%bc"
  },
  {
   "date": "2016-12-27",
   "title": "161227ノーブレーキのオリジンアワー",
   "page": "https://www.fmnaha.jp/podcast_audio/161227%e3%83%8e%e3%83%bc%e3%83%96%e3%83%ac%e3%83%bc%e3%82%ad%e3%81%ae%e3%82%aa%e3%83%aa%e3%82%b8%e3%83%b3%e3%82%a2%e3%83%af%e3%83%bc"
  }
 ]
}